AUTHORS
INSTALL
LICENSE
MANIFEST.in
NOTICE
README.rst
requirements.txt
setup.cfg
setup.py
docs/Makefile
docs/acknowledgements.rst
docs/bulkdata.rst
docs/conf.py
docs/configuration.rst
docs/faq.rst
docs/index.rst
docs/installation.rst
docs/introduction.rst
docs/make.bat
docs/quickstart.rst
docs/screenshots.rst
docs/usage.rst
docs/images/admin-sections.png
docs/images/dynamic-zone-edit.png
docs/images/zone-edit.png
docs/images/zone-export.png
docs/images/zone-import.png
docs/images/zone-list.png
src/django_powerdns_manager.egg-info/PKG-INFO
src/django_powerdns_manager.egg-info/SOURCES.txt
src/django_powerdns_manager.egg-info/dependency_links.txt
src/django_powerdns_manager.egg-info/not-zip-safe
src/django_powerdns_manager.egg-info/top_level.txt
src/powerdns_manager/__init__.py
src/powerdns_manager/actions.py
src/powerdns_manager/admin.py
src/powerdns_manager/forms.py
src/powerdns_manager/models.py
src/powerdns_manager/routers.py
src/powerdns_manager/settings.py
src/powerdns_manager/signal_cb.py
src/powerdns_manager/tests.py
src/powerdns_manager/urls.py
src/powerdns_manager/utils.py
src/powerdns_manager/views.py
src/powerdns_manager/fixtures/default_pdns_groups.json
src/powerdns_manager/locale/el/LC_MESSAGES/django.po
src/powerdns_manager/management/__init__.py
src/powerdns_manager/management/commands/__init__.py
src/powerdns_manager/management/commands/exportzones.py
src/powerdns_manager/management/commands/importaxfr.py
src/powerdns_manager/management/commands/importzones.py
src/powerdns_manager/migrations/0001_initial.py
src/powerdns_manager/migrations/0002_auto_20150114_1403.py
src/powerdns_manager/migrations/0003_record_disabled.py
src/powerdns_manager/migrations/0004_auto_20150114_1507.py
src/powerdns_manager/migrations/0005_auto_20150311_1002.py
src/powerdns_manager/migrations/0006_auto_20151018_0256.py
src/powerdns_manager/migrations/__init__.py
src/powerdns_manager/templates/powerdns_manager/domain_changeform.html
src/powerdns_manager/templates/powerdns_manager/domain_changelist.html
src/powerdns_manager/templates/powerdns_manager/template/create_zone.html
src/powerdns_manager/templates/powerdns_manager/zone/clone.html
src/powerdns_manager/templates/powerdns_manager/zone/set_ttl.html
