Metadata-Version: 1.1
Name: django-powerdns-manager
Version: 0.2.6a1
Summary: django-powerdns-manager is a web based PowerDNS administration panel.
Home-page: http://www.codetrax.org/projects/django-powerdns-manager
Author: George Notaras
Author-email: gnot@g-loaded.eu
License: Apache License version 2
Download-URL: https://bitbucket.org/gnotaras/django-powerdns-manager
Platform: any
Classifier: Development Status :: 3 - Alpha
Classifier: Environment :: Web Environment
Classifier: Framework :: Django
Classifier: Intended Audience :: Developers
Classifier: License :: OSI Approved :: Apache Software License
Classifier: Natural Language :: English
Classifier: Operating System :: OS Independent
Classifier: Programming Language :: Python
Classifier: Topic :: Internet :: Name Service (DNS)
Classifier: Topic :: System :: Systems Administration
Classifier: Topic :: Internet :: WWW/HTTP :: Dynamic Content :: CGI Tools/Libraries
Classifier: Topic :: Software Development :: Libraries :: Application Frameworks
Classifier: Topic :: Software Development :: Libraries :: Python Modules
